.gitignore
.pre-commit-config.yaml
LICENSE
MANIFEST.in
README.md
pyproject.toml
setup.py
.github/dependabot.yml
.github/release-drafter.yml
.github/workflows/codeql.yml
.github/workflows/deploy.yml
.github/workflows/release-drafter.yml
img/mnt_dark.svg
img/mnt_light.svg
src/mnt/__init__.py
src/mnt.designer.egg-info/PKG-INFO
src/mnt.designer.egg-info/SOURCES.txt
src/mnt.designer.egg-info/dependency_links.txt
src/mnt.designer.egg-info/entry_points.txt
src/mnt.designer.egg-info/requires.txt
src/mnt.designer.egg-info/top_level.txt
src/mnt/designer/app.py
src/mnt/designer/static/favicon.ico
src/mnt/designer/static/mnt_dark.svg
src/mnt/designer/static/tum_logo.svg
src/mnt/designer/static/css/styles.css
src/mnt/designer/static/gates/AND_DIN.svg
src/mnt/designer/static/gates/BUFC.svg
src/mnt/designer/static/gates/BUFK.svg
src/mnt/designer/static/gates/BUF_DIN.svg
src/mnt/designer/static/gates/INV_DIN.svg
src/mnt/designer/static/gates/NOR_DIN.svg
src/mnt/designer/static/gates/OR_DIN.svg
src/mnt/designer/static/gates/XNOR_DIN.svg
src/mnt/designer/static/gates/XOR_DIN.svg
src/mnt/designer/static/js/script.js
src/mnt/designer/templates/index.html