Metadata-Version: 2.4
Name: mnt.designer
Version: 0.1.2
Summary: MNT Designer - An MNT tool for designing FCN circuits
Author-email: Simon Hofmann <simon.t.hofmann@tum.de>
License: MIT License
Project-URL: Homepage, https://github.com/cda-tum/mntdesigner
Project-URL: Bug Tracker, https://github.com/cda-tum/mntdesigner/issues
Project-URL: Discussions, https://github.com/cda-tum/mntdesigner/discussions
Project-URL: Research, https://www.cda.cit.tum.de/research/nanotech/
Keywords: MNT,field-coupled nanocomputing,design
Classifier: Development Status :: 4 - Beta
Classifier: Intended Audience :: Developers
Classifier: License :: OSI Approved :: MIT License
Classifier: Operating System :: Microsoft :: Windows
Classifier: Operating System :: MacOS
Classifier: Operating System :: POSIX :: Linux
Classifier: Programming Language :: Python :: 3 :: Only
Classifier: Programming Language :: Python :: 3.9
Classifier: Programming Language :: Python :: 3.10
Classifier: Programming Language :: Python :: 3.11
Classifier: Programming Language :: Python :: 3.12
Classifier: Intended Audience :: Science/Research
Classifier: Natural Language :: English
Classifier: Topic :: Scientific/Engineering :: Electronic Design Automation (EDA)
Requires-Python: >=3.9
License-File: LICENSE
Requires-Dist: flask>=2.0.0
Requires-Dist: packaging>=21.0
Requires-Dist: requests>=2.31.0
Requires-Dist: mnt.pyfiction>=0.6.8
Provides-Extra: test
Requires-Dist: pytest>=7.2; extra == "test"
Provides-Extra: coverage
Requires-Dist: mnt.designer[test]; extra == "coverage"
Requires-Dist: pytest-cov[toml]; extra == "coverage"
Provides-Extra: dev
Requires-Dist: mnt.designer[coverage]; extra == "dev"
Dynamic: license-file
